bootstring/__init__.py
bootstring/decode.py
bootstring/encode.py
bootstring/generalized_variable_length_integers.py
bootstring-1.0.1.dist-info/METADATA
bootstring-1.0.1.dist-info/WHEEL
bootstring-1.0.1.dist-info/licenses/LICENSE
bootstring-1.0.1.dist-info/RECORD
