Metadata-Version: 2.1
Name: bootstring
Version: 1.0.1
Summary: Bootstring encoding and decoding (RFC 3492)
Project-URL: Homepage, https://github.com/frereit/bootstring
Project-URL: Issues, https://github.com/frereit/bootstring/issues
Author-email: Frederik Reiter <hi@frereit.de>
License-File: LICENSE
Classifier: License :: OSI Approved :: The Unlicense (Unlicense)
Classifier: Operating System :: OS Independent
Classifier: Programming Language :: Python :: 3
Requires-Python: >=3.8
Provides-Extra: dev
Requires-Dist: black; extra == 'dev'
Requires-Dist: mypy; extra == 'dev'
Requires-Dist: pytest; extra == 'dev'
